fast_luhn/__init__.py
fast_luhn/fast_luhn.cpython-35m-x86_64-linux-gnu.so
fast_luhn/fast_luhn.cpython-36m-x86_64-linux-gnu.so
fast_luhn-0.1.5.dist-info/LICENSE.txt
fast_luhn-0.1.5.dist-info/top_level.txt
fast_luhn-0.1.5.dist-info/WHEEL
fast_luhn-0.1.5.dist-info/METADATA
fast_luhn-0.1.5.dist-info/RECORD
