Metadata-Version: 2.1
Name: fast-luhn
Version: 0.1.5
Summary: Fast Luhn algorithm
Home-page: https://github.com/cybermatt/fast-luhn
Author: Matt Stroganov
Author-email: strmatvey@gmail.com
License: MIT
Keywords: luhn validation
Platform: UNKNOWN
Classifier: Development Status :: 4 - Beta
Classifier: License :: OSI Approved :: MIT License
Classifier: Intended Audience :: Developers
Classifier: Operating System :: POSIX :: Linux
Classifier: Operating System :: MacOS :: MacOS X
Classifier: Programming Language :: Rust
Classifier: Programming Language :: Python
Classifier: Programming Language :: Python :: 3
Classifier: Programming Language :: Python :: 3.5
Classifier: Programming Language :: Python :: 3.6
Classifier: Programming Language :: Python :: 3.7
Classifier: Programming Language :: Python :: 3.8
Classifier: Programming Language :: Python :: 3.9
